frontly/__init__.py
frontly/models.py
frontly/urls.py
frontly/views.py
frontly/migrations/0001_initial.py
frontly/migrations/__init__.py
frontly/static/trix/LICENSE.txt
frontly/static/trix/trix.css
frontly/static/trix/trix_2.0.0.umd.js
frontly/static/trix/trix_2.0.0.umd.min.js
frontly/templates/frontly/editor_img.html
frontly/templates/frontly/editor_input.html
frontly/templates/frontly/editor_textarea.html
frontly/templates/frontly/editor_timepicker.html
frontly/templatetags/__init__.py
frontly/templatetags/frontly.py
django_frontly-1.0.4.dist-info/LICENSE.txt
django_frontly-1.0.4.dist-info/METADATA
django_frontly-1.0.4.dist-info/WHEEL
django_frontly-1.0.4.dist-info/top_level.txt
django_frontly-1.0.4.dist-info/RECORD
