Metadata-Version: 2.1
Name: django-frontly
Version: 1.0.4
Summary: The easiest way to build views for Django.
Home-page: https://github.com/edmenendez/django-frontly
Author: Ed Menendez
Author-email: ed@menendez.com
Project-URL: Bug Tracker, https://github.com/edmenendez/django-frontly/issues
Project-URL: repository, https://github.com/edmenendez/django-frontly
Classifier: Programming Language :: Python :: 3
Classifier: License :: OSI Approved :: MIT License
Classifier: Operating System :: OS Independent
Requires-Python: >=3.6
License-File: LICENSE.txt
Requires-Dist: Django >=3.2
